crowtit/__init__.py
crowtit/advanced.py
crowtit/categorical.py
crowtit/eda.py
crowtit/generator.py
crowtit/heatmap.py
crowtit/numeric.py
crowtit/parallel.py
crowtit/utils.py
crowtit-0.2.dist-info/LICENSE
crowtit-0.2.dist-info/METADATA
crowtit-0.2.dist-info/WHEEL
crowtit-0.2.dist-info/top_level.txt
crowtit-0.2.dist-info/RECORD
