Metadata-Version: 2.1
Name: crowtit
Version: 0.2
Summary: Simple Exploratory Data Analysis tool.
Home-page: https://github.com/darkhan-ai/vizdata
License: MIT
License-File: LICENSE
Requires-Dist: pandas
Requires-Dist: matplotlib
Requires-Dist: seaborn
